pycine/__init__.py
pycine/cine.py
pycine/color.py
pycine/file.py
pycine/linLUT.py
pycine/raw.py
pycine/cli/__init__.py
pycine/cli/pfs_meta.py
pycine/cli/pfs_raw.py
pycine-0.3.2.dist-info/LICENSE
pycine-0.3.2.dist-info/METADATA
pycine-0.3.2.dist-info/WHEEL
pycine-0.3.2.dist-info/entry_points.txt
pycine-0.3.2.dist-info/top_level.txt
pycine-0.3.2.dist-info/RECORD
