Metadata-Version: 2.1
Name: pycine
Version: 0.3.2
Summary: This package allows handling of .cine files created by Vision Research Phantom® cameras.
Home-page: https://github.com/ottomatic-io/pycine
Author: Ben Hagen
Author-email: ben@ottomatic.io
License: UNKNOWN
Platform: UNKNOWN
Classifier: Programming Language :: Python :: 3 :: Only
Classifier: License :: OSI Approved :: GNU General Public License v3 or later (GPLv3+)
Classifier: Operating System :: OS Independent
Requires-Dist: click
Requires-Dist: docopt
Requires-Dist: opencv-python
Requires-Dist: colorama
